setup.cfg
setup.py
jne/__init__.py
jne/api.py
jne/constants.py
jne/exceptions.py
jne/utils.py
py_jne.egg-info/PKG-INFO
py_jne.egg-info/SOURCES.txt
py_jne.egg-info/dependency_links.txt
py_jne.egg-info/pbr.json
py_jne.egg-info/requires.txt
py_jne.egg-info/top_level.txt