Metadata-Version: 1.1
Name: py-jne
Version: 0.1.3
Summary: PyJNE is a tool to simplify the user in using the JNE API such as tracking stuff, check tariffs and others.
Home-page: https://github.com/kangfend/py-jne
Author: Sutrisno Efendi
Author-email: kangfend@gmail.com
License: MIT
Download-URL: https://github.com/kangfend/py-jne/tarball/0.1.3
Keywords: JNE,Tracking,Courier,Indonesia
Platform: UNKNOWN
Classifier: Development Status :: 3 - Alpha
Classifier: Intended Audience :: Developers
Classifier: Programming Language :: Python
Classifier: License :: OSI Approved :: MIT License
Classifier: Operating System :: OS Independent
Classifier: Topic :: Internet :: WWW/HTTP
Classifier: Topic :: Software Development :: Libraries :: Python Modules
